Metadata-Version: 2.1
Name: yahoo-finance-data
Version: 0.0.9
Summary: Retreive data (quote, historical, financial, statistics) from Yahoo Finance.
Home-page: https://github.com/BoGs567/yahoo-finance-data
Author: Sophocles
Author-email: nikitidis567@gmail.com
License: MIT
Download-URL: https://github.com/BoGs567/yahoo-finance-data/archive/refs/tags/0.0.9.tar.gz
Keywords: Yahoo,finance,data,Financial,finance,yahoo finance,yahoo-finance,yahoo data,yahoo finance data,yahoo-finance-data
Platform: UNKNOWN
Classifier: Development Status :: 3 - Alpha
Classifier: Intended Audience :: Developers
Classifier: Topic :: Software Development :: Build Tools
Classifier: License :: OSI Approved :: MIT License
Classifier: Programming Language :: Python :: 3
License-File: LICENCE.txt
